imtherapy_tmb/__init__.py
imtherapy_tmb/ft_tmb.py
imtherapy_tmb-0.0.0.dist-info/entry_points.txt
imtherapy_tmb-0.0.0.dist-info/WHEEL
imtherapy_tmb-0.0.0.dist-info/METADATA
imtherapy_tmb-0.0.0.dist-info/RECORD
