Metadata-Version: 2.1
Name: imtherapy-tmb
Version: 0.0.0
Summary: Tumor mutation burden feature transformation module for imtherapy
License: MIT
Author: pwwang
Author-email: pwwang@pwwang.com
Requires-Python: >=3.7,<4.0
Classifier: License :: OSI Approved :: MIT License
Classifier: Programming Language :: Python :: 3
Classifier: Programming Language :: Python :: 3.7
Classifier: Programming Language :: Python :: 3.8
Requires-Dist: imtherapy
Requires-Dist: pipen
